nullval/__init__.py
nullval/auto.py
nullval/lagrange_interpolation.py
nullval/linear_interpolation.py
nullval/loader.py
nullval/polynomial_interpolation.py
nullval/rough.py
nullval/spline_interpolation.py
nullval/trigonometric_interpolation.py
nullval-0.2.0.dist-info/LICENSE
nullval-0.2.0.dist-info/METADATA
nullval-0.2.0.dist-info/WHEEL
nullval-0.2.0.dist-info/RECORD
