Metadata-Version: 2.1
Name: nullval
Version: 0.2.0
Summary: A package for the treatment of nullvalues and outliers in your data set using various mathematical approaches 
Home-page: https://github.com/Mukullight/nullval
License: MIT
Keywords: finance,dataloader,outliers_finder,Nullvalue_finder,
Author: Mukul namagiri
Author-email: mukulnamagiri1@gmail.com
Requires-Python: >=3.9.19,<4.0.0
Classifier: License :: OSI Approved :: MIT License
Classifier: Operating System :: OS Independent
Classifier: Programming Language :: Python :: 3
Classifier: Programming Language :: Python :: 3.10
Classifier: Programming Language :: Python :: 3.11
Classifier: Programming Language :: Python :: 3.12
Classifier: Programming Language :: Python :: 3.6
Classifier: Programming Language :: Python :: 3.7
Classifier: Programming Language :: Python :: 3.8
Classifier: Programming Language :: Python :: 3.9
Requires-Dist: matplotlib (==3.5.1)
Requires-Dist: numpy (==1.21.4)
Requires-Dist: pandas (==1.3.3)
Requires-Dist: plotly (==5.5.0)
Requires-Dist: scikit-learn (==0.24.2)
Requires-Dist: seaborn (==0.11.2)
Requires-Dist: statsmodels (==0.13.0)
Requires-Dist: tensorflow (==2.8.0)
Project-URL: Repository, https://github.com/Mukullight/nullval
